dots_editor/FreeMono.ttf
dots_editor/__init__.py
dots_editor/__main__.py
dots_editor/core.py
dots_editor/utf8_braille.py
dots_editor-0.3.7.dist-info/DESCRIPTION.rst
dots_editor-0.3.7.dist-info/METADATA
dots_editor-0.3.7.dist-info/RECORD
dots_editor-0.3.7.dist-info/WHEEL
dots_editor-0.3.7.dist-info/entry_points.txt
dots_editor-0.3.7.dist-info/metadata.json
dots_editor-0.3.7.dist-info/top_level.txt
