Metadata-Version: 2.0
Name: dots-editor
Version: 0.3.7
Summary: A six-key brailler emulator written in python.
Home-page: https://github.com/Gailbear/dots-editor
Author: Gail Terman
Author-email: gterman@gmail.com
License: MIT
Keywords: braile pygame editor
Platform: UNKNOWN
Classifier: Development Status :: 2 - Pre-Alpha
Classifier: Environment :: Other Environment
Classifier: Intended Audience :: Education
Classifier: License :: OSI Approved :: MIT License
Classifier: Operating System :: OS Independent
Classifier: Programming Language :: Python :: 2
Classifier: Programming Language :: Python :: 2.7
Classifier: Programming Language :: Python :: 2 :: Only
Classifier: Topic :: Text Editors
Classifier: Topic :: Text Editors :: Text Processing
Requires-Dist: argparse
Requires-Dist: pygame
Requires-Dist: setuptools-scm
